runtogether/__init__.py
runtogether/command.py
runtogether/handles.py
runtogether/process.py
runtogether/utils.py
runtogether/worker_types.py
runtogether/workers.py
runtogether-0.0.4.0.dist-info/METADATA
runtogether-0.0.4.0.dist-info/RECORD
runtogether-0.0.4.0.dist-info/WHEEL
runtogether-0.0.4.0.dist-info/entry_points.txt
runtogether-0.0.4.0.dist-info/top_level.txt
