Metadata-Version: 2.1
Name: runtogether
Version: 0.0.4.0
Summary: 多端口代理/类gunicorn
Home-page: https://github.com/csy5621080/runtogether
Author: 小成
Author-email: 499938136@qq.com
License: UNKNOWN
Platform: UNKNOWN
Requires-Dist: psutil
Requires-Dist: argparse
